Metadata-Version: 1.1
Name: django-form-utils-bootstrap3
Version: 0.2.0
Summary: Render forms with fieldsets using Bootstrap markup via django-form-utils and django-bootstrap3
Home-page: https://github.com/federicobond/django-form-utils-bootstrap3
Author: Federico Bond
Author-email: federicobond@gmail.com
License: UNKNOWN
Platform: UNKNOWN
Classifier: Development Status :: 4 - Beta
Classifier: Environment :: Web Environment
Classifier: Intended Audience :: Developers
Classifier: License :: OSI Approved :: MIT License
Classifier: Operating System :: OS Independent
Classifier: Programming Language :: Python
Classifier: Programming Language :: Python :: 2
Classifier: Programming Language :: Python :: 2.7
Classifier: Programming Language :: Python :: 3
Classifier: Programming Language :: Python :: 3.5
Classifier: Framework :: Django
